clusterfun/__init__.py
clusterfun/app.py
clusterfun/config.py
clusterfun/constants.py
clusterfun/frontend/404.html
clusterfun/frontend/_next/static/0L8U1RGbBQqzpAEgBP-4y/_buildManifest.js
clusterfun/frontend/_next/static/0L8U1RGbBQqzpAEgBP-4y/_ssgManifest.js
clusterfun/frontend/_next/static/0t2IpDcBx6FIaFpL5-DTX/_buildManifest.js
clusterfun/frontend/_next/static/0t2IpDcBx6FIaFpL5-DTX/_ssgManifest.js
clusterfun/frontend/_next/static/7K0stYTjLuE1ieiHwaOY8/_buildManifest.js
clusterfun/frontend/_next/static/7K0stYTjLuE1ieiHwaOY8/_ssgManifest.js
clusterfun/frontend/_next/static/9m8W0thtsOjMrVxSpss7G/_buildManifest.js
clusterfun/frontend/_next/static/9m8W0thtsOjMrVxSpss7G/_ssgManifest.js
clusterfun/frontend/_next/static/FajzyA8s2dBSB6nVAodLv/_buildManifest.js
clusterfun/frontend/_next/static/FajzyA8s2dBSB6nVAodLv/_ssgManifest.js
clusterfun/frontend/_next/static/P5xyy85ON_Ic7d-vfYKXs/_buildManifest.js
clusterfun/frontend/_next/static/P5xyy85ON_Ic7d-vfYKXs/_ssgManifest.js
clusterfun/frontend/_next/static/U2JWEnXogvGKNw9dZYznH/_buildManifest.js
clusterfun/frontend/_next/static/U2JWEnXogvGKNw9dZYznH/_ssgManifest.js
clusterfun/frontend/_next/static/chunks/22.94ebc66962dcd0f8.js
clusterfun/frontend/_next/static/chunks/23-8126128752749016.js
clusterfun/frontend/_next/static/chunks/23-916fe2f1983668e3.js
clusterfun/frontend/_next/static/chunks/472-07a7dd51a787971b.js
clusterfun/frontend/_next/static/chunks/483-2d99a375fdcaeaa9.js
clusterfun/frontend/_next/static/chunks/500-9855c0cda36bb0be.js
clusterfun/frontend/_next/static/chunks/500-9beb637c2f8db305.js
clusterfun/frontend/_next/static/chunks/771-1510a54548bf26b3.js
clusterfun/frontend/_next/static/chunks/8.d9282dffb5cd6834.js
clusterfun/frontend/_next/static/chunks/86-fdf3fe7d49e1a681.js
clusterfun/frontend/_next/static/chunks/870fdd6f-080da6c9b87ec5a2.js
clusterfun/frontend/_next/static/chunks/870fdd6f-4049d31c55f7218c.js
clusterfun/frontend/_next/static/chunks/870fdd6f-51765f2c6413dd54.js
clusterfun-0.6.1.dist-info/LICENSE
clusterfun-0.6.1.dist-info/METADATA
clusterfun-0.6.1.dist-info/WHEEL
clusterfun-0.6.1.dist-info/entry_points.txt
clusterfun-0.6.1.dist-info/RECORD
