Metadata-Version: 2.1
Name: clusterfun
Version: 0.6.1
Summary: Clusterfun - a plotting library to inspect data
Author: Jochem Gietema
Author-email: jochem@giete.ma
Requires-Python: >=3.9,<4.0
Classifier: Programming Language :: Python :: 3
Classifier: Programming Language :: Python :: 3.9
Classifier: Programming Language :: Python :: 3.10
Classifier: Programming Language :: Python :: 3.11
Classifier: Programming Language :: Python :: 3.12
Requires-Dist: boto3 (>=1.26.0,<2.0.0)
Requires-Dist: fastapi
Requires-Dist: orjson
Requires-Dist: pandas (>=2.0.0,<3.0.0)
Requires-Dist: pillow
Requires-Dist: pyarrow (>=13,<17)
Requires-Dist: requests
Requires-Dist: urllib3 (<2)
Requires-Dist: uvicorn
